README.md
setup.py
mysql_to_json.egg-info/PKG-INFO
mysql_to_json.egg-info/SOURCES.txt
mysql_to_json.egg-info/dependency_links.txt
mysql_to_json.egg-info/entry_points.txt
mysql_to_json.egg-info/requires.txt
mysql_to_json.egg-info/top_level.txt
mysqljson/__init__.py
mysqljson/__main__.py