Metadata-Version: 1.1
Name: mysql-to-json
Version: 1.0.0
Summary: Connects to a MySQL database and exports selected data to JSON.
Home-page: https://github.com/sethblack/mysql-to-json
Author: Seth Black
Author-email: sblack@sethserver.com
License: UNKNOWN
Keywords: mysql,json,database,db,export,export tool,export utility
Platform: UNKNOWN
Classifier: Topic :: Database
Classifier: Programming Language :: Python
Classifier: Programming Language :: Python :: 3
Classifier: Programming Language :: Python :: 3 :: Only
Classifier: Development Status :: 5 - Production/Stable
Classifier: Environment :: Console
Classifier: Intended Audience :: Developers
Classifier: License :: OSI Approved :: BSD License
Classifier: Operating System :: OS Independent
